matterix/__init__.py
matterix/datasets.py
matterix/functions.py
matterix/nn.py
matterix/ops.py
matterix/optim.py
matterix/tensor.py
matterix/utils.py
tests/__init__.py
tests/test_add.py
tests/test_div.py
tests/test_exp.py
tests/test_functions.py
tests/test_matmul.py
tests/test_methods.py
tests/test_mul.py
tests/test_sub.py
tests/test_sum.py
tests/test_tensor.py
MatterIx-1.1.1.dist-info/LICENSE
MatterIx-1.1.1.dist-info/METADATA
MatterIx-1.1.1.dist-info/WHEEL
MatterIx-1.1.1.dist-info/top_level.txt
MatterIx-1.1.1.dist-info/RECORD
