Metadata-Version: 2.1
Name: MatterIx
Version: 1.1.1
Summary: Just another deep learning framework
Home-page: https://github.com/SiddeshSambasivam/MatterIx
Author: Siddesh Sambasivam Suseela
Author-email: plutocrat45@gmail.com
License: UNKNOWN
Project-URL: Bug Tracker, https://github.com/SiddeshSambasivam/MatterIx/issues
Platform: UNKNOWN
Classifier: Programming Language :: Python :: 3
Classifier: License :: OSI Approved :: MIT License
Classifier: Operating System :: OS Independent
Requires-Python: >=3.8.0
License-File: LICENSE
Requires-Dist: appdirs (==1.4.4)
Requires-Dist: attrs (==21.2.0)
Requires-Dist: black (==21.6b0)
Requires-Dist: certifi (==2021.5.30)
Requires-Dist: click (==8.0.1)
Requires-Dist: iniconfig (==1.1.1)
Requires-Dist: mypy-extensions (==0.4.3)
Requires-Dist: numpy (==1.20.3)
Requires-Dist: packaging (==20.9)
Requires-Dist: pathspec (==0.8.1)
Requires-Dist: pluggy (==0.13.1)
Requires-Dist: py (==1.10.0)
Requires-Dist: pyparsing (==2.4.7)
Requires-Dist: pytest (==6.2.4)
Requires-Dist: regex (==2021.4.4)
Requires-Dist: toml (==0.10.2)
